rtl/layer_norm_vec.v

module layer_norm_vec #(parameter WIDTH=16, parameter FRAC=8, parameter DIM=4)(
    input  signed [WIDTH*DIM-1:0] x_in,
    output reg signed [WIDTH*DIM-1:0] y_out
);
    integer i;
    reg signed [WIDTH-1:0] x [0:DIM-1];
    reg signed [WIDTH+8:0] sum;
    reg signed [WIDTH-1:0] mean;

    reg signed [WIDTH-1:0] diff [0:DIM-1];
    reg signed [2*WIDTH-1:0] diff_sq [0:DIM-1];
    reg signed [2*WIDTH+4:0] var_sum;
    reg signed [WIDTH-1:0] var_q;
    reg signed [WIDTH-1:0] inv_std;
    reg signed [2*WIDTH-1:0] mult;

    function signed [WIDTH-1:0] inv_std_approx;
        input signed [WIDTH-1:0] v;
        begin
            if (v <= 16'sd16)        inv_std_approx = 16'sd256;
            else if (v <= 16'sd64)   inv_std_approx = 16'sd181;
            else if (v <= 16'sd128)  inv_std_approx = 16'sd128;
            else if (v <= 16'sd256)  inv_std_approx = 16'sd90;
            else if (v <= 16'sd512)  inv_std_approx = 16'sd64;
            else                     inv_std_approx = 16'sd45;
        end
    endfunction

    always @(*) begin
        for (i=0; i<DIM; i=i+1)
            x[i] = x_in[WIDTH*i +: WIDTH];

        sum = 0;
        for (i=0; i<DIM; i=i+1)
            sum = sum + x[i];
        mean = sum / DIM;

        var_sum = 0;
        for (i=0; i<DIM; i=i+1) begin
            diff[i] = x[i] - mean;
            diff_sq[i] = diff[i] * diff[i];
            var_sum = var_sum + (diff_sq[i] >>> FRAC);
        end

        var_q   = var_sum / DIM;
        inv_std = inv_std_approx(var_q + 16'sd1);

        for (i=0; i<DIM; i=i+1) begin
            mult = diff[i] * inv_std;
            y_out[WIDTH*i +: WIDTH] = mult >>> FRAC;
        end
    end
endmodule

rtl/softmax_lut.v

module softmax_lut #(parameter WIDTH=16, parameter FRAC=8, parameter LEN=4)(
    input  signed [WIDTH*LEN-1:0] x_in,
    output reg signed [WIDTH*LEN-1:0] x_out
);
    integer i;
    reg signed [WIDTH-1:0] x [0:LEN-1];
    reg signed [WIDTH-1:0] xmax;
    reg signed [WIDTH-1:0] s [0:LEN-1];
    reg signed [WIDTH-1:0] e [0:LEN-1];
    reg signed [WIDTH+8:0] esum;
    reg signed [WIDTH-1:0] tmp;

    function signed [WIDTH-1:0] exp_approx;
        input signed [WIDTH-1:0] v;
        begin
            if (v >= 0)               exp_approx = 16'sd256;
            else if (v >= -16'sd64)   exp_approx = 16'sd200;
            else if (v >= -16'sd128)  exp_approx = 16'sd155;
            else if (v >= -16'sd192)  exp_approx = 16'sd121;
            else if (v >= -16'sd256)  exp_approx = 16'sd94;
            else if (v >= -16'sd384)  exp_approx = 16'sd57;
            else if (v >= -16'sd512)  exp_approx = 16'sd35;
            else                      exp_approx = 16'sd8;
        end
    endfunction

    always @(*) begin
        for (i=0; i<LEN; i=i+1)
            x[i] = x_in[WIDTH*i +: WIDTH];

        xmax = x[0];
        for (i=1; i<LEN; i=i+1)
            if (x[i] > xmax) xmax = x[i];

        esum = 0;
        for (i=0; i<LEN; i=i+1) begin
            s[i] = x[i] - xmax;
            e[i] = exp_approx(s[i]);
            esum = esum + e[i];
        end

        for (i=0; i<LEN; i=i+1) begin
            tmp = (e[i] <<< FRAC) / esum;
            x_out[WIDTH*i +: WIDTH] = tmp;
        end
    end
endmodule

rtl/fp_multiplier.v

module fp_multiplier #(parameter WIDTH=16, parameter FRAC=8)(
    input  signed [WIDTH-1:0] a,
    input  signed [WIDTH-1:0] b,
    output reg signed [WIDTH-1:0] result
);
    reg signed [2*WIDTH-1:0] full;
    reg signed [2*WIDTH-1:0] shifted;

    always @(*) begin
        full    = a * b;
        shifted = full >>> FRAC;

        if (shifted > 32767)
            result = 16'sd32767;
        else if (shifted < -32768)
            result = -16'sd32768;
        else
            result = shifted[WIDTH-1:0];
    end
endmodule

rtl/dot_product.v

module dot_product #(parameter WIDTH=16, parameter FRAC=8, parameter LEN=4)(
    input  signed [WIDTH*LEN-1:0] a,
    input  signed [WIDTH*LEN-1:0] b,
    output reg signed [WIDTH-1:0] result
);
    wire signed [WIDTH-1:0] p [0:LEN-1];

    genvar i;
    generate
        for (i=0; i<LEN; i=i+1) begin : MULS
            fp_multiplier #(.WIDTH(WIDTH), .FRAC(FRAC)) mul_i (
                .a(a[WIDTH*i +: WIDTH]),
                .b(b[WIDTH*i +: WIDTH]),
                .result(p[i])
            );
        end
    endgenerate

    integer k;
    reg signed [WIDTH+8:0] acc;

    always @(*) begin
        acc = 0;
        for (k=0; k<LEN; k=k+1)
            acc = acc + p[k];

        if (acc > 32767)
            result = 16'sd32767;
        else if (acc < -32768)
            result = -16'sd32768;
        else
            result = acc[WIDTH-1:0];
    end
endmodule

tb/tb_task2.v

`timescale 1ns/1ps
module tb_task2;

    reg  signed [15:0] ma, mb;
    wire signed [15:0] mres;
    fp_multiplier #(.WIDTH(16), .FRAC(8)) MUL (.a(ma), .b(mb), .result(mres));

    reg  signed [63:0] da, db;
    wire signed [15:0] dres;
    dot_product #(.WIDTH(16), .FRAC(8), .LEN(4)) DOT (.a(da), .b(db), .result(dres));

    reg  signed [63:0] sx_in;
    wire signed [63:0] sx_out;
    softmax_lut #(.WIDTH(16), .FRAC(8), .LEN(4)) SFT (.x_in(sx_in), .x_out(sx_out));

    reg  signed [63:0] lx_in;
    wire signed [63:0] ly_out;
    layer_norm_vec #(.WIDTH(16), .FRAC(8), .DIM(4)) LNM (.x_in(lx_in), .y_out(ly_out));

    initial begin
        $dumpfile("/content/project/waveforms/task2.vcd");
        $dumpvars(0, tb_task2);

        ma = 16'sd256;  mb = 16'sd256;   #10;
        $display("[MUL] 1.0 * 1.0 = %0d (exp 256)", mres);

        ma = 16'sd512;  mb = 16'sd128;   #10;
        $display("[MUL] 2.0 * 0.5 = %0d (exp 256)", mres);

        ma = -16'sd256; mb = 16'sd256;   #10;
        $display("[MUL] -1.0 * 1.0 = %0d (exp -256)", mres);

        ma = 16'sd32767; mb = 16'sd32767; #10;
        $display("[MUL] SAT = %0d (exp 32767)", mres);

        da = {16'sd256,16'sd256,16'sd256,16'sd256};
        db = {16'sd256,16'sd256,16'sd256,16'sd256};
        #10;
        $display("[DOT] [1,1,1,1].[1,1,1,1] = %0d (exp 1024)", dres);

        da = {16'sd512,16'sd128,16'sd256,16'sd0};
        db = {16'sd256,16'sd512,16'sd768,16'sd1024};
        #10;
        $display("[DOT] [2,.5,1,0].[1,2,3,4] = %0d (exp 1536)", dres);

        sx_in = {16'sd256,16'sd256,16'sd256,16'sd256};
        #10;
        $display("[SFT] uniform: %0d %0d %0d %0d (exp ~64 each)",
            sx_out[15:0], sx_out[31:16], sx_out[47:32], sx_out[63:48]);

        sx_in = {16'sd512,16'sd256,16'sd0,-16'sd256};
        #10;
        $display("[SFT] varied:  %0d %0d %0d %0d",
            sx_out[15:0], sx_out[31:16], sx_out[47:32], sx_out[63:48]);

        lx_in = {16'sd1024,16'sd768,16'sd512,16'sd256};
        #10;
        $display("[LNM] vec1: %0d %0d %0d %0d",
            ly_out[15:0], ly_out[31:16], ly_out[47:32], ly_out[63:48]);

        lx_in = {16'sd512,16'sd512,16'sd512,16'sd512};
        #10;
        $display("[LNM] vec2: %0d %0d %0d %0d (exp near 0s)",
            ly_out[15:0], ly_out[31:16], ly_out[47:32], ly_out[63:48]);

        $finish;
    end
endmodule

waveforms/task2.vcd
$date
	Tue Mar 31 06:36:35 2026
$end
$version
	Icarus Verilog
$end
$timescale
	1ps
$end
$scope module tb_task2 $end
$var wire 64 ! sx_out [63:0] $end
$var wire 16 " mres [15:0] $end
$var wire 64 # ly_out [63:0] $end
$var wire 16 $ dres [15:0] $end
$var reg 64 % da [63:0] $end
$var reg 64 & db [63:0] $end
$var reg 64 ' lx_in [63:0] $end
$var reg 16 ( ma [15:0] $end
$var reg 16 ) mb [15:0] $end
$var reg 64 * sx_in [63:0] $end
$scope module DOT $end
$var wire 64 + a [63:0] $end
$var wire 64 , b [63:0] $end
$var reg 25 - acc [24:0] $end
$var reg 16 . result [15:0] $end
$var integer 32 / k [31:0] $end
$scope begin MULS[0] $end
$scope module mul_i $end
$var wire 16 0 a [15:0] $end
$var wire 16 1 b [15:0] $end
$var reg 32 2 full [31:0] $end
$var reg 16 3 result [15:0] $end
$var reg 32 4 shifted [31:0] $end
$upscope $end
$upscope $end
$scope begin MULS[1] $end
$scope module mul_i $end
$var wire 16 5 a [15:0] $end
$var wire 16 6 b [15:0] $end
$var reg 32 7 full [31:0] $end
$var reg 16 8 result [15:0] $end
$var reg 32 9 shifted [31:0] $end
$upscope $end
$upscope $end
$scope begin MULS[2] $end
$scope module mul_i $end
$var wire 16 : a [15:0] $end
$var wire 16 ; b [15:0] $end
$var reg 32 < full [31:0] $end
$var reg 16 = result [15:0] $end
$var reg 32 > shifted [31:0] $end
$upscope $end
$upscope $end
$scope begin MULS[3] $end
$scope module mul_i $end
$var wire 16 ? a [15:0] $end
$var wire 16 @ b [15:0] $end
$var reg 32 A full [31:0] $end
$var reg 16 B result [15:0] $end
$var reg 32 C shifted [31:0] $end
$upscope $end
$upscope $end
$upscope $end
$scope module LNM $end
$var wire 64 D x_in [63:0] $end
$var reg 16 E inv_std [15:0] $end
$var reg 16 F mean [15:0] $end
$var reg 32 G mult [31:0] $end
$var reg 25 H sum [24:0] $end
$var reg 16 I var_q [15:0] $end
$var reg 37 J var_sum [36:0] $end
$var reg 64 K y_out [63:0] $end
$var integer 32 L i [31:0] $end
$scope function inv_std_approx $end
$var reg 16 M v [15:0] $end
$upscope $end
$upscope $end
$scope module MUL $end
$var wire 16 N a [15:0] $end
$var wire 16 O b [15:0] $end
$var reg 32 P full [31:0] $end
$var reg 16 Q result [15:0] $end
$var reg 32 R shifted [31:0] $end
$upscope $end
$scope module SFT $end
$var wire 64 S x_in [63:0] $end
$var reg 25 T esum [24:0] $end
$var reg 16 U tmp [15:0] $end
$var reg 64 V x_out [63:0] $end
$var reg 16 W xmax [15:0] $end
$var integer 32 X i [31:0] $end
$scope function exp_approx $end
$var reg 16 Y v [15:0] $end
$upscope $end
$upscope $end
$upscope $end
$enddefinitions $end
#0
$dumpvars
bx Y
bx X
bx W
bx V
bx U
bx T
bx S
b100000000 R
b100000000 Q
b10000000000000000 P
b100000000 O
b100000000 N
bx M
bx L
bx K
bx J
bx I
bx H
bx G
bx F
bx E
bx D
bx C
bx B
bx A
bx @
bx ?
bx >
bx =
bx <
bx ;
bx :
bx 9
bx 8
bx 7
bx 6
bx 5
bx 4
bx 3
bx 2
bx 1
bx 0
bx /
bx .
bx -
bx ,
bx +
bx *
b100000000 )
b100000000 (
bx '
bx &
bx %
bx $
bx #
b100000000 "
bx !
$end
#10000
b10000000 )
b10000000 O
b1000000000 (
b1000000000 N
#20000
b1111111100000000 "
b1111111100000000 Q
b11111111111111111111111100000000 R
b11111111111111110000000000000000 P
b100000000 )
b100000000 O
b1111111100000000 (
b1111111100000000 N
#30000
b111111111111111 "
b111111111111111 Q
b1111111111111100000000 R
b111111111111110000000000000001 P
b111111111111111 )
b111111111111111 O
b111111111111111 (
b111111111111111 N
#40000
b10000000000 $
b10000000000 .
b100 /
b10000000000 -
b100000000 3
b100000000 4
b10000000000000000 2
b100000000 8
b100000000 9
b10000000000000000 7
b100000000 =
b100000000 >
b10000000000000000 <
b100000000 B
b100000000 C
b10000000000000000 A
b100000000 1
b100000000 6
b100000000 ;
b100000000 @
b100000000 0
b100000000 5
b100000000 :
b100000000 ?
b100000000000000010000000000000001000000000000000100000000 &
b100000000000000010000000000000001000000000000000100000000 ,
b100000000000000010000000000000001000000000000000100000000 %
b100000000000000010000000000000001000000000000000100000000 +
#50000
b11000000000 $
b11000000000 .
b100 /
b11000000000 -
b1100000000 8
b1100000000 9
b110000000000000000 7
b0 3
b0 4
b0 2
b1000000000 B
b1000000000 C
b100000000000000000 A
b10000000000 1
b1100000000 6
b1000000000 ;
b0 0
b10000000 :
b1000000000 ?
b100000000000000100000000000000011000000000000010000000000 &
b100000000000000100000000000000011000000000000010000000000 ,
b1000000000000000001000000000000001000000000000000000000000 %
b1000000000000000001000000000000001000000000000000000000000 +
#60000
b1000000000000000100000000000000010000000000000001000000 !
b1000000000000000100000000000000010000000000000001000000 V
b1000000 U
b0 Y
b10000000000 T
b100000000 W
b100 X
b100000000000000010000000000000001000000000000000100000000 *
b100000000000000010000000000000001000000000000000100000000 S
#70000
b10100110000000000011110100000000000101100000000000000101 !
b10100110000000000011110100000000000101100000000000000101 V
b10100110 U
b0 Y
b110001001 T
b1000000000 W
b100 X
b1000000000000000010000000000000000000000001111111100000000 *
b1000000000000000010000000000000000000000001111111100000000 S
#80000
b1100000000000000010000011111111111000001111111110100000 #
b1100000000000000010000011111111111000001111111110100000 K
b110000000000000 G
b1000000 E
b101000001 M
b101000000 I
b10100000000 J
b1010000000 F
b101000000000 H
b100 L
b10000000000000000110000000000000010000000000000000100000000 '
b10000000000000000110000000000000010000000000000000100000000 D
#90000
b0 #
b0 K
b0 G
b100000000 E
b1 M
b0 I
b0 J
b1000000000 F
b100000000000 H
b100 L
b1000000000000000100000000000000010000000000000001000000000 '
b1000000000000000100000000000000010000000000000001000000000 D
